{"stats":{"minecraft:picked_up":{"minecraft:wooden_axe":37,"minecraft:golden_carrot":97,"minecraft:potion":1,"minecraft:trident":1,"minecraft:shield":31,"minecraft:elytra":30,"minecraft:smooth_sandstone_slab":1,"minecraft:iron_leggings":41,"minecraft:leather_boots":23,"minecraft:firework_rocket":343,"minecraft:arrow":129,"minecraft:sea_pickle":64,"minecraft:bow":35,"minecraft:player_head":35,"minecraft:glass_bottle":1,"minecraft:iron_sword":37},"minecraft:used":{"minecraft:red_sandstone_stairs":58,"minecraft:oak_log":158,"minecraft:quartz_bricks":25,"minecraft:trident":51,"minecraft:water_bucket":53,"minecraft:sea_lantern":191,"minecraft:iron_bars":60,"minecraft:brick_wall":7,"minecraft:firework_rocket":154,"minecraft:brick_stairs":7,"minecraft:chiseled_sandstone":11,"minecraft:quartz_pillar":470,"minecraft:lodestone":36,"minecraft:snow_block":19,"minecraft:quartz_slab":232,"minecraft:polished_andesite_stairs":50,"minecraft:lantern":17,"minecraft:grass_block":2,"minecraft:barrier":18,"minecraft:oak_planks":51,"minecraft:polished_andesite":351,"minecraft:smooth_sandstone":38,"minecraft:quartz_block":395,"minecraft:smooth_sandstone_slab":10,"minecraft:stripped_warped_stem":77,"minecraft:iron_sword":64,"minecraft:sandstone":1,"minecraft:shield":13,"minecraft:stone":200,"minecraft:cut_sandstone":111,"minecraft:cut_red_sandstone":100,"minecraft:quartz_stairs":834,"minecraft:player_head":1,"minecraft:smooth_sandstone_stairs":71,"minecraft:chiseled_red_sandstone":40,"minecraft:golden_carrot":1,"minecraft:potion":43,"minecraft:bow":99,"minecraft:cut_sandstone_slab":5,"minecraft:prismarine_bricks":40,"minecraft:prismarine_brick_stairs":35,"minecraft:chain":18,"minecraft:stone_stairs":14,"minecraft:sea_pickle":17,"minecraft:chiseled_quartz_block":19,"minecraft:purple_wool":6,"minecraft:milk_bucket":1,"minecraft:polished_deepslate_stairs":141},"minecraft:custom":{"minecraft:time_since_rest":62403,"minecraft:sprint_one_cm":209968,"minecraft:damage_taken":44170,"minecraft:walk_one_cm":771725,"minecraft:damage_blocked_by_shield":625,"minecraft:drop":326,"minecraft:damage_dealt":3897,"minecraft:fly_one_cm":3196647,"minecraft:player_kills":27,"minecraft:crouch_one_cm":9539,"minecraft:play_time":303980,"minecraft:deaths":70,"minecraft:sneak_time":9619,"minecraft:walk_under_water_one_cm":280428,"minecraft:aviate_one_cm":291318,"minecraft:jump":1199,"minecraft:leave_game":11,"minecraft:walk_on_water_one_cm":103088,"minecraft:time_since_death":62403,"minecraft:climb_one_cm":1974,"minecraft:total_world_time":303980,"minecraft:fall_one_cm":79917},"minecraft:dropped":{"minecraft:sea_pickle":257,"minecraft:player_head":1,"minecraft:wooden_axe":2,"minecraft:arrow":65,"minecraft:elytra":1},"minecraft:killed_by":{"minecraft:player":43}},"DataVersion":2730}